acab/__init__.py
acab/acab.py
acab-1.0.3.dist-info/METADATA
acab-1.0.3.dist-info/WHEEL
acab-1.0.3.dist-info/entry_points.txt
acab-1.0.3.dist-info/top_level.txt
acab-1.0.3.dist-info/RECORD
