Metadata-Version: 2.4
Name: acab
Version: 1.0.3
Summary: Alignments Comparing and Benchmarking (ACAB): инструмент для сравнения множественных выравниваний
Author: pirat
Author-email: piratvanek@gmail.com
Classifier: Programming Language :: Python :: 3
Classifier: Operating System :: OS Independent
Requires-Python: >=3.6
Dynamic: author
Dynamic: author-email
Dynamic: classifier
Dynamic: description
Dynamic: description-content-type
Dynamic: requires-python
Dynamic: summary
